fluidx3d.cp311-win_amd64.pyd
OpenCL/include/CL/cl.h
OpenCL/include/CL/cl.hpp
OpenCL/include/CL/cl_ext.h
OpenCL/include/CL/cl_gl.h
OpenCL/include/CL/cl_gl_ext.h
OpenCL/include/CL/cl_platform.h
OpenCL/include/CL/opencl.h
OpenCL/lib/OpenCL.lib
X11/include/X11/X.h
X11/include/X11/XKBlib.h
X11/include/X11/Xdefs.h
X11/include/X11/Xfuncproto.h
X11/include/X11/Xlib.h
X11/include/X11/Xosdefs.h
X11/include/X11/Xutil.h
X11/include/X11/keysym.h
X11/include/X11/keysymdef.h
X11/include/X11/extensions/XKB.h
X11/include/X11/extensions/XKBstr.h
X11/include/X11/extensions/Xrandr.h
X11/include/X11/extensions/Xrender.h
X11/include/X11/extensions/randr.h
X11/include/X11/extensions/render.h
fluidx3d-2.16.3.dist-info/licenses/LICENSE.md
fluidx3d-2.16.3.dist-info/METADATA
fluidx3d-2.16.3.dist-info/WHEEL
fluidx3d-2.16.3.dist-info/top_level.txt
fluidx3d-2.16.3.dist-info/RECORD
