Metadata-Version: 2.4
Name: fluidx3d
Version: 2.16.3
Summary: Real-time interactive Lattice Boltzmann CFD with full GPU acceleration and graphics
Home-page: https://github.com/gitcnd/FluidX3D-2.16-python
Author: Dr. Moritz Lehmann (original), AuraFriday (Python bindings)
Author-email: 
License: GPLv3
Project-URL: Homepage, https://github.com/gitcnd/FluidX3D-2.16-python
Project-URL: Repository, https://github.com/gitcnd/FluidX3D-2.16-python
Project-URL: Bug Tracker, https://github.com/gitcnd/FluidX3D-2.16-python/issues
Project-URL: Original FluidX3D, https://github.com/ProjectPhysX/FluidX3D
Keywords: cfd,lattice-boltzmann,fluid-dynamics,gpu,opencl,computational-physics,simulation,interactive
Classifier: Development Status :: 4 - Beta
Classifier: Intended Audience :: Science/Research
Classifier: Intended Audience :: Developers
Classifier: Programming Language :: Python :: 3
Classifier: Programming Language :: Python :: 3.11
Classifier: Programming Language :: Python :: 3.12
Classifier: Programming Language :: Python :: 3.13
Classifier: Programming Language :: Python :: 3.14
Classifier: Programming Language :: C++
Classifier: Topic :: Scientific/Engineering :: Physics
Classifier: Topic :: Scientific/Engineering :: Visualization
Classifier: License :: OSI Approved :: GNU General Public License v3 (GPLv3)
Classifier: Operating System :: Microsoft :: Windows
Requires-Python: >=3.11
License-File: LICENSE.md
Requires-Dist: pybind11>=2.6.0
Provides-Extra: dev
Requires-Dist: pytest>=6.0; extra == "dev"
Requires-Dist: build>=0.10.0; extra == "dev"
Requires-Dist: twine>=4.0.0; extra == "dev"
Dynamic: home-page
Dynamic: license-file
Dynamic: requires-python
